pythonic_fp/queues/__init__.py
pythonic_fp/queues/__init__.pyi
pythonic_fp/queues/de.py
pythonic_fp/queues/de.pyi
pythonic_fp/queues/fifo.py
pythonic_fp/queues/fifo.pyi
pythonic_fp/queues/lifo.py
pythonic_fp/queues/lifo.pyi
pythonic_fp/queues/py.typed
pythonic_fp_queues-5.1.1.dist-info/licenses/LICENSE
pythonic_fp_queues-5.1.1.dist-info/WHEEL
pythonic_fp_queues-5.1.1.dist-info/METADATA
pythonic_fp_queues-5.1.1.dist-info/RECORD
