Metadata-Version: 2.4
Name: pythonic-fp-queues
Version: 5.1.1
Summary: Queues
Keywords: queue,fifo,lifo,dqueue
Author-email: "Geoffrey R. Scheller" <geoffrey@scheller.com>
Requires-Python: >=3.12
Classifier: Development Status :: 5 - Production/Stable
Classifier: Framework :: Pytest
Classifier: Intended Audience :: Developers
Classifier: License :: OSI Approved :: Apache Software License
Classifier: Operating System :: OS Independent
Classifier: Programming Language :: Python :: 3.13
Classifier: Typing :: Typed
License-File: LICENSE
Requires-Dist: pythonic-fp-circulararray>=6.0.1
Requires-Dist: pythonic-fp-fptools>=5.2.0
Requires-Dist: pytest>=8.4.1 ; extra == "test"
Project-URL: Changelog, https://github.com/grscheller/pythonic-fp-queues/blob/main/CHANGELOG.rst
Project-URL: Documentation, https://grscheller.github.io/pythonic-fp/queues/development/build/html/
Project-URL: Homepage, https://grscheller.github.io/pythonic-fp/homepage/build/html/
Project-URL: Source, https://github.com/grscheller/pythonic-fp-queues
Provides-Extra: test
